precli/__init__.py
precli/__main__.py
precli/i18n.py
precli/cli/__init__.py
precli/cli/init.py
precli/cli/main.py
precli/core/__init__.py
precli/core/argument.py
precli/core/artifact.py
precli/core/call.py
precli/core/comparison.py
precli/core/config.py
precli/core/cwe.py
precli/core/fix.py
precli/core/kind.py
precli/core/level.py
precli/core/linecache.py
precli/core/loader.py
precli/core/location.py
precli/core/metrics.py
precli/core/redos.py
precli/core/result.py
precli/core/run.py
precli/core/status.py
precli/core/suppression.py
precli/core/symtab.py
precli/core/tool.py
precli/core/utils.py
precli/locale/de/LC_MESSAGES/messages.mo
precli/locale/de/LC_MESSAGES/messages.po
precli/locale/en_GB/LC_MESSAGES/messages.mo
precli/locale/en_GB/LC_MESSAGES/messages.po
precli/locale/es/LC_MESSAGES/messages.mo
precli/locale/es/LC_MESSAGES/messages.po
precli/locale/fr/LC_MESSAGES/messages.mo
precli/locale/fr/LC_MESSAGES/messages.po
precli/locale/it/LC_MESSAGES/messages.mo
precli/locale/it/LC_MESSAGES/messages.po
precli/locale/ja/LC_MESSAGES/messages.mo
precli/locale/ja/LC_MESSAGES/messages.po
precli/locale/ko/LC_MESSAGES/messages.mo
precli/locale/ko/LC_MESSAGES/messages.po
precli/locale/pt_BR/LC_MESSAGES/messages.mo
precli/locale/pt_BR/LC_MESSAGES/messages.po
precli/locale/ru/LC_MESSAGES/messages.mo
precli/locale/ru/LC_MESSAGES/messages.po
precli/locale/zh_CN/LC_MESSAGES/messages.mo
precli/locale/zh_CN/LC_MESSAGES/messages.po
precli/locale/zh_TW/LC_MESSAGES/messages.mo
precli/locale/zh_TW/LC_MESSAGES/messages.po
precli/parsers/__init__.py
precli/parsers/basic.py
precli/parsers/go.py
precli/parsers/java.py
precli/parsers/node_types.py
precli/parsers/python.py
precli/renderers/__init__.py
precli/renderers/detailed.py
precli/renderers/json.py
precli/renderers/markdown.py
precli/renderers/plain.py
precli/rules/__init__.py
precli/rules/go/__init__.py
precli/rules/go/stdlib/__init__.py
precli/rules/go/stdlib/crypto_unrestricted_bind.py
precli/rules/go/stdlib/crypto_weak_cipher.py
precli-0.8.3.dist-info/licenses/LICENSE
precli-0.8.3.dist-info/METADATA
precli-0.8.3.dist-info/WHEEL
precli-0.8.3.dist-info/entry_points.txt
precli-0.8.3.dist-info/pbr.json
precli-0.8.3.dist-info/top_level.txt
precli-0.8.3.dist-info/RECORD
